brown_clustering/__init__.py
brown_clustering/core.py
brown_clustering/data.py
brown_clustering/defaultvaluedict.py
brown_clustering/helper.py
brown_clustering-0.1.6.dist-info/LICENSE
brown_clustering-0.1.6.dist-info/METADATA
brown_clustering-0.1.6.dist-info/WHEEL
brown_clustering-0.1.6.dist-info/top_level.txt
brown_clustering-0.1.6.dist-info/RECORD
