Metadata-Version: 2.1
Name: brown-clustering
Version: 0.1.6
Summary: Fast Brown Clustering
Home-page: https://github.com/helpmefindaname/BrownClustering
Author: bfuchs
Author-email: benedikt.fuchs.staw@hotmail.com
License: MIT
Requires-Python: >=3.7
License-File: LICENSE
Requires-Dist: numpy
Requires-Dist: numba
Requires-Dist: tqdm
Provides-Extra: dev
Requires-Dist: pytest ; extra == 'dev'
Requires-Dist: pytest-mypy ; extra == 'dev'
Requires-Dist: pytest-profiling ; extra == 'dev'
Requires-Dist: pytest-flake8 ; extra == 'dev'
Requires-Dist: flake8 (<4.0.0) ; extra == 'dev'
Requires-Dist: flake8-isort ; extra == 'dev'
